{
    "$schema": "https://schema.management.azure.com/schemas/2015-01-01/deploymentParameters.json#",
    "contentVersion": "1.0.0.0",
    "parameters": {
        "factoryName": {
            "value": ""
        },
        "AzureSqlDW_connectionString": {
            "value": ""
        },
        "ADLSGen2_accountKey": {
            "value": ""
        },
        "AzureStorage_connectionString": {
            "value": ""
        },
        "CDMParser_URL": {
            "value": "https://<FunctionAppName>.azurewebsites.net/api/Parse"
        },
        "AzureDatabricks_domain": {
            "value": ""
        },
        "AzureDatabricks_accessToken": {
            "value": ""
        },
        "ADLSGen2_url": {
            "value": ""
        }
    }
}